tests
greenlet_tornado
