Metadata-Version: 1.1
Name: greenlet-tornado
Version: 1.1.3
Summary: An easy way to seamlessly use Greenlet with Tornado
Home-page: http://github.com/tatiana/greenlet_tornado
Author: jphaas1, simonrad, rodsenra, tati_alchueyr (tatiana)
Author-email: UNKNOWN
License: MIT License
Download-URL: http://pypi.python.org/pypi/greenlet_tornado
Platform: UNKNOWN
Classifier: Development Status :: 5 - Production/Stable
Classifier: Environment :: Web Environment
Classifier: Intended Audience :: Developers
Classifier: Operating System :: OS Independent
Classifier: Programming Language :: Python
